2022-01-26
--------------------------------

ÀÚ¹Ù·Î HelloJava ÇÁ·Î±×·¥ ¸¸µé¾î º¸±â 

ÀÚ¹ÙÇÁ·Î±×·¥Àº ¸¸µé ¶§ ÇÊ¿äÇÑ µµ±¸
----------------------------
1. jdk : jdk 1.8
2. ÆíÁý±â : ¿¡µðÆ® ÇÃ·¯½º 
3. ½ÇÇàµµ±¸ : MS DOS, console
4. API

ÀÚ¹ÙÇÁ·Î±×·¥ ¸¸µé±â
----------------------------
1. ÀÚ¹ÙÇÁ·Î±×·¥ È®ÀåÀÚ´Â .java
	ex) ÀÚ¹ÙÇÁ·Î±×·¥ÀÌ¸§.java

2. ÆíÁý±â¿¡¼­ ÀÚ¹Ù ¼Ò½º·Î ÀÚ¹Ù ÇÁ·Î±×·¥À» ¸¸µç´Ù.

3. È®ÀåÀÚ¸¦ .java ·Î ÀúÀåÇÑ´Ù.

4. ÀÚ¹ÙÇÁ·Î±×·¥À» javac.exe ¸í·É¾î·Î ÄÄÆÄÀÏÇÑ´Ù.
	ÄÄÆÄÀÏÀÌ ¼º°øµÇ¸é ÀÚ¹ÙÇÁ·Î±×·¥ÀÌ¸§.class È­ÀÏÀ» »ý¼ºÇÑ´Ù.
	
	javac ÀÚ¹ÙÇÁ·Î±×·¥ÀÌ¸§.java ---> ÀÚ¹ÙÇÁ·Î±×·¥ÀÌ¸§.class

5. ÄÄÆÄÀÏµÈ ÆÄÀÏÀ» java.exe ¸í·É¾î·Î ½ÇÇàÇÑ´Ù.
	´Ü java ¸í·É¾î·Î ½ÇÇàÇÒ ¶§´Â ÀÚ¹ÙÇÁ·Î±×·¥ÀÌ¸§ ¸¸ »ç¿ëÇÑ´Ù.
	java ÀÚ¹ÙÇÁ·Î±×·¥ÀÌ¸§


ÇÃ·§Æû  platform
------------------
À©µµ¿ì ¸Æ ¸®´ª½º 
À¯´Ð½º 
	IBM À¯´Ð½º
	HP À¯´Ð½º
	¿À¶óÅ¬ ¼Ö¶ó¸®½º ....

ÄÄÆÄÀÏ·¯ ??
--------------
ÇÁ·Î±×·¥ ¾ð¾î¸¦ ÄÄÇ»ÅÍ°¡ ¾Ë¾Æº¼ ¼ö ÀÖ°Ô ¹Ù²Ù´Â °Í 

javac.exe ½ÇÇàÈ­ÀÏ : ÄÄÆÄÀÏ·¯ 
ÀÚ¹Ù ¾ð¾î¸¦ ÀÚ¹Ù °¡»ó¸Ó½Å(ÀÚ¹Ù ¹öÃ¶¸Ó½Å, JVM)ÀÌ ¾Ë¾Æº¼ ¼ö ÀÖ°Ô ¹Ù²Ù´Â °Í : ¹ÙÀÌÆ® ÄÚµå byte code

1. HelloJava.java  ÆÄÀÏ 10.JExam Æú´õ¿¡ ÀÖ´ÂÁö È®ÀÎ 
----------------------------------------------
C:\00.KOSMO108\10.JExam>dir/w HelloJava.java
 C µå¶óÀÌºêÀÇ º¼·ý: system
 º¼·ý ÀÏ·Ã ¹øÈ£: B2DB-7002

 C:\00.KOSMO108\10.JExam µð·ºÅÍ¸®

HelloJava.java
               1°³ ÆÄÀÏ                 950 ¹ÙÀÌÆ®
               0°³ µð·ºÅÍ¸®  196,588,273,664 ¹ÙÀÌÆ® ³²À½


2. HelloJava.java ÆÄÀÏ ³»¿ë º¸±â 
----------------------------------------------
C:\00.KOSMO108\10.JExam>help type
ÅØ½ºÆ® ÆÄÀÏÀÇ ³»¿ëÀ» º¸¿©ÁÝ´Ï´Ù.

TYPE [µå¶óÀÌºê:][°æ·Î]ÆÄÀÏÀÌ¸§
----------------------------------------------
C:\00.KOSMO108\10.JExam>type HelloJava.java

// HelloJava.java ÇÁ·Î±×·¥ ¸¸µé±â
// HelloJava ÇÁ·Î±×·¥Àº ÄÜ¼Ö¿¡ "¾È³ç ÀÚ¹Ù" ¹®ÀÚ¿­À» Ãâ·ÂÇÏ±â ÇÁ·Î±×·¥ÀÌ´Ù.

// HelloJava.java ÇÁ·Î±×·¥Àº C:\00.KOSMO108\10.JExam Æú´õ¿¡ ÀúÀåÇÑ´Ù.

public class HelloJava {

        public static void main(String args[]){

                System.out.println("¾È³ç ÀÚ¹Ù");
        }
}

/*
1. HelloJava ÇÁ·Î±×·¥À» ÆíÁý±â¿¡¼­ ¸¸µç´Ù.

2. HelloJava ÇÁ·Î±×·¥À» .java È®ÀåÀÚ·Î ÀúÀåÇÑ´Ù.

3. HelloJava ÇÁ·Î±×·¥À» ÄÄÆÄÀÏ ÇÏ±â À§ÇØ¼­
        HelloJava.java ÇÁ·Î±×·¥ÀÌ ÀÖ´Â Æú´õ¸¦ Ã£¾Æ°£´Ù.
        C:\00.KOSMO108\10.JExam\HelloJava.java
        ÄÜ¼ÖÃ¢¿¡¼­ ÇØ´ç µð·ºÅä¸®±îÁö Ã£¾Æ°£´Ù.

        javac ¸í·É¾î·Î ÄÄÆÄÀÏ ÇÑ´Ù.
        C:\00.KOSMO108\10.JExam>javac ÇÁ·Î±×·¥ÀÌ¸§.È®ÀåÀÚ
        C:\00.KOSMO108\10.JExam>javac HelloJava.java


        ÄÄÆÄÀÏÀÌ Àß µÇ¸é
        C:\00.KOSMO108\10.JExam>dir HelloJava.class

4. HelloJava.class È­ÀÏÀ» java ¸í·É¾î·Î ½ÇÇàÀ» ÇÑ´Ù.

        C:\00.KOSMO108\10.JExam>java ÇÁ·Î±×·¥ÀÌ¸§¸¸
        C:\00.KOSMO108\10.JExam>java HelloJava
        ¾È³ç ÀÚ¹Ù
*/


3. javac ÄÄÆÄÀÏ·¯ ¸í·É¾î·Î HelloJava.java ÄÄÆÄÀÏ ÇÏ±â 
   ÄÄÆÄÀÏÀÌ ¼º°øÇÏ¸é HelloJava.class Å¬·¡½º È­ÀÏÀÌ »ý¼º µÈ´Ù. 
----------------------------------------------
C:\00.KOSMO108\10.JExam>javac HelloJava.java

C:\00.KOSMO108\10.JExam>dir/w HelloJava.class
 C µå¶óÀÌºêÀÇ º¼·ý: system
 º¼·ý ÀÏ·Ã ¹øÈ£: B2DB-7002

 C:\00.KOSMO108\10.JExam µð·ºÅÍ¸®

HelloJava.class
               1°³ ÆÄÀÏ                 425 ¹ÙÀÌÆ®
               0°³ µð·ºÅÍ¸®  196,587,548,672 ¹ÙÀÌÆ® ³²À½

4. type ¸í·É¾î·Î HelloJava.class ¹ÙÀÌÆ® ÄÚµå ³»¿ë º¸±â 
----------------------------------------------
C:\00.KOSMO108\10.JExam>type HelloJava.class
Êþº¾4
      
<init>()VCodeLineNumberTablemain([Ljava/lang/String;)V
?ˆë…• ?ë°”HelloJava.java


5. java ¸í·É¾î HelloJava Å¬·¡½º È­ÀÏ ½ÇÇàÇÏ±â 
   java ¸í·É¾î·Î HelloJava Å¬·¡½º È­ÀÏÀ» ½ÇÇàÇÒ ¶§´Â .class È®ÀåÀÚ¸¦ »ý·«ÇÑ´Ù.
----------------------------------------------
C:\00.KOSMO108\10.JExam>java HelloJava
¾È³ç ÀÚ¹Ù

6. javap ¿ªÄÄÆÄÀÏ·¯·Î HelloJava Å¬·¡½º¸¦ ¿ªÄÄÆÄÀÏ ÇÏ±â 
   ¿ªÄÄÆÄÀÏ·¯´Â ÀÚ¹ÙÅ¬·¡½º ¹ÙÀÌÆ®ÄÚµå¸¦ ¼Ò½ºÄÚµå·Î º¯È¯ÇÏ´Â °Í 
----------------------------------------------
C:\00.KOSMO108\10.JExam>javap HelloJava
Compiled from "HelloJava.java"
public class HelloJava {
  public HelloJava();
  public static void main(java.lang.String[]);
}

7. javap ¿ªÄÄÆÄÀÏ·¯·Î HelloJava Å¬·¡½º¸¦ ¿ªÄÄÆÄÀÏÀ» 
   -verbose ¿É¼ÇÀ» ÀÌ¿ëÇØ¼­ ÀÚ¼¼ÇÏ°Ô ¿ªÄÄÆÄÀÏ ÇÑ´Ù.
----------------------------------------------
C:\00.KOSMO108\10.JExam>javap -verbose HelloJava
Classfile /C:/00.KOSMO108/10.JExam/HelloJava.class
  Last modified 2022. 1. 26; size 425 bytes
  MD5 checksum d647fbd85ad43a1a6efaa18c164a2270
  Compiled from "HelloJava.java"
public class HelloJava
  minor version: 0
  major version: 52
  flags: ACC_PUBLIC, ACC_SUPER
Constant pool:
   #1 = Methodref          #6.#15         // java/lang/Object."<init>":()V
   #2 = Fieldref           #16.#17        // java/lang/System.out:Ljava/io/PrintStream;
   #3 = String             #18            // ¾È³ç ÀÚ¹Ù
   #4 = Methodref          #19.#20        // java/io/PrintStream.println:(Ljava/lang/String;)V
   #5 = Class              #21            // HelloJava
   #6 = Class              #22            // java/lang/Object
   #7 = Utf8               <init>
   #8 = Utf8               ()V
   #9 = Utf8               Code
  #10 = Utf8               LineNumberTable
  #11 = Utf8               main
  #12 = Utf8               ([Ljava/lang/String;)V
  #13 = Utf8               SourceFile
  #14 = Utf8               HelloJava.java
  #15 = NameAndType        #7:#8          // "<init>":()V
  #16 = Class              #23            // java/lang/System
  #17 = NameAndType        #24:#25        // out:Ljava/io/PrintStream;
  #18 = Utf8               ¾È³ç ÀÚ¹Ù
  #19 = Class              #26            // java/io/PrintStream
  #20 = NameAndType        #27:#28        // println:(Ljava/lang/String;)V
  #21 = Utf8               HelloJava
  #22 = Utf8               java/lang/Object
  #23 = Utf8               java/lang/System
  #24 = Utf8               out
  #25 = Utf8               Ljava/io/PrintStream;
  #26 = Utf8               java/io/PrintStream
  #27 = Utf8               println
  #28 = Utf8               (Ljava/lang/String;)V
{
  public HelloJava();
    descriptor: ()V
    flags: ACC_PUBLIC
    Code:
      stack=1, locals=1, args_size=1
         0: aload_0
         1: invokespecial #1                  // Method java/lang/Object."<init>":()V
         4: return
      LineNumberTable:
        line 7: 0

  public static void main(java.lang.String[]);
    descriptor: ([Ljava/lang/String;)V
    flags: ACC_PUBLIC, ACC_STATIC
    Code:
      stack=2, locals=1, args_size=1
         0: getstatic     #2                  // Field java/lang/System.out:Ljava/io/PrintStream;
         3: ldc           #3                  // String ¾È³ç ÀÚ¹Ù
         5: invokevirtual #4                  // Method java/io/PrintStream.println:(Ljava/lang/String;)V
         8: return
      LineNumberTable:
        line 11: 0
        line 12: 8
}
SourceFile: "HelloJava.java"



*.jar : java archive : ÆÄÀÏ ¾ÐÃà 


1. ÄÄÆÄÀÏ ÇÒ ¶§ »ç¿ëµÇ´Â ÀÚ¿ø 
-----------------------------------------
// javac -verbose Hello.java
C:\00.KOSMO108\10.JExam>javac -verbose Hello.java
[parsing started RegularFileObject[Hello.java]]
[parsing completed 17ms]
[search path for source files: .]
[search path for class files: 
C:\Program Files\Java\jdk1.8.0_202\jre\lib\resources.jar,
==================================================================
C:\Program Files\Java\jdk1.8.0_202\jre\lib\rt.jar,
==================================================================
C:\Program Files\Java\jdk1.8.0_202\jre\lib\sunrsasign.jar,
C:\Program Files\Java\jdk1.8.0_202\jre\lib\jsse.jar,
C:\Program Files\Java\jdk1.8.0_202\jre\lib\jce.jar,
C:\Program Files\Java\jdk1.8.0_202\jre\lib\charsets.jar,
C:\Program Files\Java\jdk1.8.0_202\jre\lib\jfr.jar,
C:\Program Files\Java\jdk1.8.0_202\jre\classes,
C:\Program Files\Java\jdk1.8.0_202\jre\lib\ext\access-bridge-64.jar,
C:\Program Files\Java\jdk1.8.0_202\jre\lib\ext\cldrdata.jar,
C:\Program Files\Java\jdk1.8.0_202\jre\lib\ext\dnsns.jar,
C:\Program Files\Java\jdk1.8.0_202\jre\lib\ext\jaccess.jar,
C:\Program Files\Java\jdk1.8.0_202\jre\lib\ext\jfxrt.jar,
C:\Program Files\Java\jdk1.8.0_202\jre\lib\ext\localedata.jar,
C:\Program Files\Java\jdk1.8.0_202\jre\lib\ext\nashorn.jar,
C:\Program Files\Java\jdk1.8.0_202\jre\lib\ext\sunec.jar,
C:\Program Files\Java\jdk1.8.0_202\jre\lib\ext\sunjce_provider.jar,
C:\Program Files\Java\jdk1.8.0_202\jre\lib\ext\sunmscapi.jar,
C:\Program Files\Java\jdk1.8.0_202\jre\lib\ext\sunpkcs11.jar,
C:\Program Files\Java\jdk1.8.0_202\jre\lib\ext\zipfs.jar,.]
[loading ZipFileIndexFileObject[C:\Program Files\Java\jdk1.8.0_202\lib\ct.sym(META-INF/sym/rt.jar/java/lang/Object.class)]]
[loading ZipFileIndexFileObject[C:\Program Files\Java\jdk1.8.0_202\lib\ct.sym(META-INF/sym/rt.jar/java/lang/String.class)]]
[checking Hello]
[loading ZipFileIndexFileObject[C:\Program Files\Java\jdk1.8.0_202\lib\ct.sym(META-INF/sym/rt.jar/java/io/Serializable.class)]]
[loading ZipFileIndexFileObject[C:\Program Files\Java\jdk1.8.0_202\lib\ct.sym(META-INF/sym/rt.jar/java/lang/AutoCloseable.class)]]
[loading ZipFileIndexFileObject[C:\Program Files\Java\jdk1.8.0_202\lib\ct.sym(META-INF/sym/rt.jar/java/lang/Byte.class)]]
[loading ZipFileIndexFileObject[C:\Program Files\Java\jdk1.8.0_202\lib\ct.sym(META-INF/sym/rt.jar/java/lang/Character.class)]]
[loading ZipFileIndexFileObject[C:\Program Files\Java\jdk1.8.0_202\lib\ct.sym(META-INF/sym/rt.jar/java/lang/Short.class)]]
[loading ZipFileIndexFileObject[C:\Program Files\Java\jdk1.8.0_202\lib\ct.sym(META-INF/sym/rt.jar/java/lang/Long.class)]]
[loading ZipFileIndexFileObject[C:\Program Files\Java\jdk1.8.0_202\lib\ct.sym(META-INF/sym/rt.jar/java/lang/Float.class)]]
[loading ZipFileIndexFileObject[C:\Program Files\Java\jdk1.8.0_202\lib\ct.sym(META-INF/sym/rt.jar/java/lang/Integer.class)]]
[loading ZipFileIndexFileObject[C:\Program Files\Java\jdk1.8.0_202\lib\ct.sym(META-INF/sym/rt.jar/java/lang/Double.class)]]
[loading ZipFileIndexFileObject[C:\Program Files\Java\jdk1.8.0_202\lib\ct.sym(META-INF/sym/rt.jar/java/lang/Boolean.class)]]
[loading ZipFileIndexFileObject[C:\Program Files\Java\jdk1.8.0_202\lib\ct.sym(META-INF/sym/rt.jar/java/lang/Void.class)]]
[loading ZipFileIndexFileObject[C:\Program Files\Java\jdk1.8.0_202\lib\ct.sym(META-INF/sym/rt.jar/java/lang/System.class)]]
[loading ZipFileIndexFileObject[C:\Program Files\Java\jdk1.8.0_202\lib\ct.sym(META-INF/sym/rt.jar/java/io/PrintStream.class)]]
[loading ZipFileIndexFileObject[C:\Program Files\Java\jdk1.8.0_202\lib\ct.sym(META-INF/sym/rt.jar/java/lang/Appendable.class)]]
[loading ZipFileIndexFileObject[C:\Program Files\Java\jdk1.8.0_202\lib\ct.sym(META-INF/sym/rt.jar/java/io/Closeable.class)]]
[loading ZipFileIndexFileObject[C:\Program Files\Java\jdk1.8.0_202\lib\ct.sym(META-INF/sym/rt.jar/java/io/FilterOutputStream.class)]]
[loading ZipFileIndexFileObject[C:\Program Files\Java\jdk1.8.0_202\lib\ct.sym(META-INF/sym/rt.jar/java/io/OutputStream.class)]]
[loading ZipFileIndexFileObject[C:\Program Files\Java\jdk1.8.0_202\lib\ct.sym(META-INF/sym/rt.jar/java/io/Flushable.class)]]
[loading ZipFileIndexFileObject[C:\Program Files\Java\jdk1.8.0_202\lib\ct.sym(META-INF/sym/rt.jar/java/lang/Comparable.class)]]
[loading ZipFileIndexFileObject[C:\Program Files\Java\jdk1.8.0_202\lib\ct.sym(META-INF/sym/rt.jar/java/lang/CharSequence.class)]]
[wrote RegularFileObject[Hello.class]]
[total 173ms]


2. ½ÇÇà ÇÒ ¶§ »ç¿ëµÇ´Â ÀÚ¿ø 
-----------------------------------------
// java -verbose
// java -verbose:[class|gc|jni]
//      »ó¼¼ Á¤º¸ Ãâ·ÂÀ» »ç¿ëÀ¸·Î ¼³Á¤ÇÕ´Ï´Ù.

C:\00.KOSMO108\10.JExam>java -verbose Hello
==================================================================
[Opened C:\Program Files\Java\jdk1.8.0_202\jre\lib\rt.jar]
==================================================================
[Loaded java.lang.Object from C:\Program Files\Java\jdk1.8.0_202\jre\lib\rt.jar]
[Loaded java.io.Serializable from C:\Program Files\Java\jdk1.8.0_202\jre\lib\rt.jar]
[Loaded java.lang.Comparable from C:\Program Files\Java\jdk1.8.0_202\jre\lib\rt.jar]
[Loaded java.lang.CharSequence from C:\Program Files\Java\jdk1.8.0_202\jre\lib\rt.jar]
[Loaded java.lang.String from C:\Program Files\Java\jdk1.8.0_202\jre\lib\rt.jar]
~~~~~~
~~~~~~
[Loaded sun.launcher.LauncherHelper$FXHelper from C:\Program Files\Java\jdk1.8.0_202\jre\lib\rt.jar]
[Loaded java.lang.Class$MethodArray from C:\Program Files\Java\jdk1.8.0_202\jre\lib\rt.jar]
[Loaded java.lang.Void from C:\Program Files\Java\jdk1.8.0_202\jre\lib\rt.jar]
Hello Java
[Loaded java.lang.Shutdown from C:\Program Files\Java\jdk1.8.0_202\jre\lib\rt.jar]
[Loaded java.lang.Shutdown$Lock from C:\Program Files\Java\jdk1.8.0_202\jre\lib\rt.jar]


ÀÚ¹Ù ¼Ò½º
-------------------------------------------------
C:\Program Files\Java\jdk1.8.0_202\src.zip
C:\Program Files\Java\jdk1.8.0_202\src\java


ÀÚ¹Ù API : Application Programming Interface
-------------------------------------------------
https://docs.oracle.com/javase/8/docs/api/
https://docs.oracle.com/javase/7/docs/api/
https://docs.oracle.com/javase/6/docs/api/



¿¹¾à¾î Å°¿öµå keyword
-----------------
https://docs.oracle.com/javase/tutorial/java/nutsandbolts/_keywords.html
Java Language Keywords
Here is a list of keywords in the Java programming language. 
You cannot use any of the following as identifiers in your programs. 
The keywords const and goto are reserved, even though they are not currently used. true, false, and null might seem like keywords, but they are actually literals; you cannot use them as identifiers in your programs.

abstract	continue	for			new			switch
assert***	default		goto*		package		synchronized
boolean		do			if			private		this
break		double		implements	protected	throw
byte		else		import		public		throws
case		enum****	instanceof	return		transient
catch		extends		int	short	try
char		final		interface	static		void
class		finally		long		strictfp**	volatile
const*		float		native		super		while
*	 	not used
**	 	added in 1.2
***	 	added in 1.4
****	 	added in 5.0
